{
  "model": "lasso",
  "energy_savings_potential": {
    "canopy_share": {
      "avg_log_reduction": 0.04546207704855364,
      "approx_pct_savings": 4.6511317063553825,
      "samples_with_savings": 412,
      "total_samples": 1000
    },
    "canopy_x_population_high_canopy_low_pop": {
      "avg_log_reduction": 0.21217421514358287,
      "approx_pct_savings": 23.636325951999204,
      "samples_with_savings": 259,
      "total_samples": 1000
    },
    "canopy_x_population_high_canopy_high_pop": {
      "avg_log_reduction": 0.0011074300735598001,
      "approx_pct_savings": 0.1108043500665401,
      "samples_with_savings": 772,
      "total_samples": 1000
    },
    "canopy_x_gdp_no_canopy_high_gdp": {
      "avg_log_reduction": 3.206568781864263e-18,
      "approx_pct_savings": 0.0,
      "samples_with_savings": 994,
      "total_samples": 1000
    },
    "canopy_x_population_medium_canopy_low_pop": {
      "avg_log_reduction": 0.47747942447508707,
      "approx_pct_savings": 61.20060940012475,
      "samples_with_savings": 11,
      "total_samples": 1000
    },
    "days_in_bin_25_30_x_canopy": {
      "avg_log_reduction": 0.035982359856301036,
      "approx_pct_savings": 3.663755989411488,
      "samples_with_savings": 278,
      "total_samples": 1000
    },
    "canopy_x_population_low_canopy_medium_pop": {
      "avg_log_reduction": 0.005536513737778389,
      "approx_pct_savings": 0.5551868554267925,
      "samples_with_savings": 965,
      "total_samples": 1000
    },
    "canopy_x_humidity_no_canopy_RH_mid": {
      "avg_log_reduction": 0.002865755785811468,
      "approx_pct_savings": 0.2869865989265419,
      "samples_with_savings": 985,
      "total_samples": 1000
    },
    "canopy_x_nightlight_medium_canopy_urban_high": {
      "avg_log_reduction": 0.007122322726965637,
      "approx_pct_savings": 0.7147746791100529,
      "samples_with_savings": 976,
      "total_samples": 1000
    },
    "days_in_bin_15_20_x_canopy": {
      "avg_log_reduction": 0.0005056274145947908,
      "approx_pct_savings": 0.05057552656833053,
      "samples_with_savings": 236,
      "total_samples": 1000
    },
    "canopy_x_nightlight_medium_canopy_urban_low": {
      "avg_log_reduction": 0.06947888452535354,
      "approx_pct_savings": 7.194942624486567,
      "samples_with_savings": 64,
      "total_samples": 1000
    },
    "canopy_x_nightlight_high_canopy_urban_high": {
      "avg_log_reduction": 0.002955046352041537,
      "approx_pct_savings": 0.29594168054167813,
      "samples_with_savings": 558,
      "total_samples": 1000
    }
  },
  "summary_statistics": {
    "total_canopy_features": 22,
    "avg_effect_across_features": -0.0008820342657969962,
    "features_with_energy_savings": 12
  }
}